CHANGELOG.md
innovationmerge/__init__.py
innovationmerge/app/__init__.py
innovationmerge/app/exceptions.py
innovationmerge/app/logger/__init__.py
innovationmerge/app/middleware/__init__.py
innovationmerge/app/routers/__init__.py
innovationmerge/app/routers/authenticate.py
innovationmerge/app/routers/sample_route.py
innovationmerge/app/sample.py
innovationmerge/app/schemas/sample_schema.py
innovationmerge/app/schemas/user_schema.py
innovationmerge/app/security.py
innovationmerge/config.py
innovationmerge/configurations/constants.py
innovationmerge/docs/api_doc.py
innovationmerge/docs/file.md
innovationmerge/scripts/test.sh
innovationmerge/src/ai/__init__.py
innovationmerge/src/ai/cpu/__init__.py
innovationmerge/src/ai/edge/__init__.py
innovationmerge/src/ai/edge/object_detection.py
innovationmerge/src/ai/gpu/__init__.py
innovationmerge/src/utils/responses.py
innovationmerge/tests/__init__.py
innovationmerge/tests/sample.py
innovationmerge/tests/test_object_detection.py
innovationmerge-1.1.3.dist-info/METADATA
innovationmerge-1.1.3.dist-info/WHEEL
innovationmerge-1.1.3.dist-info/RECORD
